AFQ/__init__.py
AFQ/_fixes.py
AFQ/registration.py
AFQ/version.py
AFQ/api/__init__.py
AFQ/api/bundle_dict.py
AFQ/api/group.py
AFQ/api/participant.py
AFQ/api/utils.py
AFQ/data/__init__.py
AFQ/data/fetch.py
AFQ/data/utils.py
AFQ/definitions/__init__.py
AFQ/definitions/image.py
AFQ/definitions/mapping.py
AFQ/definitions/utils.py
AFQ/models/QBallTP.py
AFQ/models/__init__.py
AFQ/models/csd.py
AFQ/models/dki.py
AFQ/models/dti.py
AFQ/models/fwdti.py
AFQ/recognition/__init__.py
AFQ/recognition/cleaning.py
AFQ/recognition/criteria.py
AFQ/recognition/curvature.py
AFQ/recognition/other_bundles.py
AFQ/recognition/preprocess.py
AFQ/recognition/recognize.py
AFQ/recognition/roi.py
AFQ/recognition/utils.py
AFQ/recognition/tests/__init__.py
AFQ/recognition/tests/test_other_bundles.py
AFQ/recognition/tests/test_recognition.py
AFQ/recognition/tests/test_rois.py
AFQ/recognition/tests/test_utils.py
AFQ/tasks/__init__.py
AFQ/tasks/data.py
AFQ/tasks/decorators.py
AFQ/tasks/mapping.py
AFQ/tasks/segmentation.py
AFQ/tasks/tractography.py
AFQ/tasks/utils.py
AFQ/tasks/viz.py
AFQ/tests/__init__.py
AFQ/tests/test_api.py
AFQ/tests/test_bundle_dict.py
AFQ/tests/test_csd.py
AFQ/tests/test_data.py
AFQ/tests/test_definitions.py
AFQ/tests/test_dki.py
AFQ/tests/test_dti.py
AFQ/tests/test_fixes.py
AFQ/tests/test_registration.py
AFQ/tests/test_tractography.py
AFQ/tests/test_viz.py
AFQ/tests/data/MoriGroups_Test.mat
AFQ/tests/data/WholeBrainFG_test.mat
AFQ/tests/data/mocks3/ds000102-mimic/.gitattributes
AFQ/tests/data/mocks3/ds000102-mimic/CHANGES
AFQ/tests/data/mocks3/ds000102-mimic/README
AFQ/tests/data/mocks3/ds000102-mimic/T1w.json
AFQ/tests/data/mocks3/ds000102-mimic/annex-uuid
AFQ/tests/data/mocks3/ds000102-mimic/dataset_description.json
AFQ/tests/data/mocks3/ds000102-mimic/participants.tsv
AFQ/tests/data/mocks3/ds000102-mimic/task-flanker_bold.json
AFQ/tests/data/mocks3/ds000102-mimic/.datalad/.gitattributes
AFQ/tests/data/mocks3/ds000102-mimic/.datalad/config
pyafq-2.0.1.dist-info/licenses/LICENSE
pyafq-2.0.1.dist-info/METADATA
pyafq-2.0.1.dist-info/WHEEL
pyafq-2.0.1.dist-info/top_level.txt
pyafq-2.0.1.dist-info/RECORD
