Metadata-Version: 2.4
Name: pyAFQ
Version: 2.0.1
Summary: pyAFQ: Automated Fiber Quantification ... in Python
Home-page: https://tractometry.github.io/pyAFQ
Download-URL: https://github.com/tractometry/pyAFQ
Author: pyAFQ developers
Author-email: arokem@gmail.com
Maintainer: Ariel Rokem
Maintainer-email: arokem@gmail.com
License: BSD License
Platform: OS Independent
Classifier: Development Status :: 3 - Alpha
Classifier: Environment :: Console
Classifier: Intended Audience :: Science/Research
Classifier: License :: OSI Approved :: BSD License
Classifier: Operating System :: OS Independent
Classifier: Programming Language :: Python
Classifier: Topic :: Scientific/Engineering
Requires-Python: <3.13,>=3.10
License-File: LICENSE
Requires-Dist: scikit_image>=0.14.2
Requires-Dist: dipy<1.12.0,>=1.11.0
Requires-Dist: pandas
Requires-Dist: pybids>=0.16.2
Requires-Dist: templateflow>=0.8
Requires-Dist: pimms
Requires-Dist: pydra
Requires-Dist: trx-python
Requires-Dist: ray
Requires-Dist: toml>=0.10.0
Requires-Dist: setuptools_scm[toml]<5.1.0,>=3.4.0
Requires-Dist: plotly==5.12.0
Requires-Dist: kaleido==0.2.1
Requires-Dist: imageio>=2.0.0
Requires-Dist: Pillow
Requires-Dist: matplotlib
Requires-Dist: altair
Provides-Extra: dev
Requires-Dist: docutils==0.15.2; extra == "dev"
Requires-Dist: astroid<=2.15.8; extra == "dev"
Requires-Dist: sphinx; extra == "dev"
Requires-Dist: memory-profiler; extra == "dev"
Requires-Dist: pytest==7.2.0; extra == "dev"
Requires-Dist: pytest-cov==2.10.0; extra == "dev"
Requires-Dist: flake8; extra == "dev"
Requires-Dist: sphinx_gallery; extra == "dev"
Requires-Dist: sphinx_rtd_theme; extra == "dev"
Requires-Dist: numpydoc==1.2; extra == "dev"
Requires-Dist: sphinx-autoapi; extra == "dev"
Requires-Dist: rapidfuzz; extra == "dev"
Requires-Dist: xvfbwrapper==0.2.9; extra == "dev"
Requires-Dist: moto<5.0.0,>=3.0.0; extra == "dev"
Requires-Dist: pydata-sphinx-theme; extra == "dev"
Requires-Dist: sphinx-design; extra == "dev"
Requires-Dist: myst-nb; extra == "dev"
Requires-Dist: wget; extra == "dev"
Provides-Extra: fury
Requires-Dist: fury==0.12.0; extra == "fury"
Requires-Dist: xvfbwrapper==0.2.9; extra == "fury"
Requires-Dist: ipython<=7.20.0,>=7.13.0; extra == "fury"
Provides-Extra: fsl
Requires-Dist: fslpy; extra == "fsl"
Provides-Extra: afqbrowser
Requires-Dist: AFQ-Browser>=0.3; extra == "afqbrowser"
Provides-Extra: plot
Requires-Dist: pingouin>=0.3; extra == "plot"
Requires-Dist: seaborn>=0.11.0; extra == "plot"
Requires-Dist: ipython<=7.20.0,>=7.13.0; extra == "plot"
Provides-Extra: aws
Requires-Dist: s3bids>=0.1.7; extra == "aws"
Requires-Dist: s3fs; extra == "aws"
Requires-Dist: boto3>=1.14.0; extra == "aws"
Provides-Extra: all
Requires-Dist: docutils==0.15.2; extra == "all"
Requires-Dist: astroid<=2.15.8; extra == "all"
Requires-Dist: sphinx; extra == "all"
Requires-Dist: memory-profiler; extra == "all"
Requires-Dist: pytest==7.2.0; extra == "all"
Requires-Dist: pytest-cov==2.10.0; extra == "all"
Requires-Dist: flake8; extra == "all"
Requires-Dist: sphinx_gallery; extra == "all"
Requires-Dist: sphinx_rtd_theme; extra == "all"
Requires-Dist: numpydoc==1.2; extra == "all"
Requires-Dist: sphinx-autoapi; extra == "all"
Requires-Dist: rapidfuzz; extra == "all"
Requires-Dist: xvfbwrapper==0.2.9; extra == "all"
Requires-Dist: moto<5.0.0,>=3.0.0; extra == "all"
Requires-Dist: pydata-sphinx-theme; extra == "all"
Requires-Dist: sphinx-design; extra == "all"
Requires-Dist: myst-nb; extra == "all"
Requires-Dist: wget; extra == "all"
Requires-Dist: fury==0.12.0; extra == "all"
Requires-Dist: xvfbwrapper==0.2.9; extra == "all"
Requires-Dist: ipython<=7.20.0,>=7.13.0; extra == "all"
Requires-Dist: fslpy; extra == "all"
Requires-Dist: AFQ-Browser>=0.3; extra == "all"
Requires-Dist: pingouin>=0.3; extra == "all"
Requires-Dist: seaborn>=0.11.0; extra == "all"
Requires-Dist: ipython<=7.20.0,>=7.13.0; extra == "all"
Requires-Dist: s3bids>=0.1.7; extra == "all"
Requires-Dist: s3fs; extra == "all"
Requires-Dist: boto3>=1.14.0; extra == "all"
Dynamic: download-url
Dynamic: license-file
